{"ygPerms":{"resourceCapabilityList":[{"resourceType":"GROUP","capabilities":[{"name":"READ"},{"name":"JOIN"}]},{"resourceType":"PHOTO","capabilities":[]},{"resourceType":"FILE","capabilities":[]},{"resourceType":"MEMBER","capabilities":[]},{"resourceType":"LINK","capabilities":[]},{"resourceType":"CALENDAR","capabilities":[]},{"resourceType":"DATABASE","capabilities":[]},{"resourceType":"POLL","capabilities":[]},{"resourceType":"MESSAGE","capabilities":[]},{"resourceType":"PENDING_MESSAGE","capabilities":[]},{"resourceType":"ATTACHMENTS","capabilities":[]},{"resourceType":"PHOTOMATIC_ALBUMS","capabilities":[]},{"resourceType":"MEMBERSHIP_TYPE","capabilities":[]},{"resourceType":"POST","capabilities":[]},{"resourceType":"PIN","capabilities":[]}],"groupUrl":"groups.yahoo.com","intlCode":"us"},"comscore":"pageview_candidate","ygData":{"title":"GLBT News Group","webDomain":"https://groups.yahoo.com/","emailDomain":"yahoogroups.com","domainUrlPrefix":"https://groups.yahoo.com/","description":"<div id=\"ygrps-yiv-1484192106\">GLBT_News is part of the FtM-trans Network and consists of posted GLBTQI articles from multiple sources, with a tilt towards the interests of the bisexual, transgender, queer & questioning, intersex, and asexual communities. GLBT_News works to include article compilations and member posts.  Member posts may cover legislation, jobs, political movements, action alerts, crime and punishment, rallies, national and regional event dates, and discussion relevent to the GLBTQI communities. <br><br>List discussion isn&#39;t required for membership. Members with access to other lists are encouraged to post articles not already appearing but please exercise caution and include full posts/links/info. Please contribute what you can and forward or otherwise use what you need. <br><br>NO SPAM OR ADS FOR SEXUALLY EXPLICIT MATERIAL!! MEMBERS WHO POST THIS SORT OF THING WILL BE REMOVED AND BANNED FROM THE GROUP!<br><br>News and opinion material provided to this YahooGroup&#39;s subscribers is distributed without profit or monetary gain to those who have expressed an interest in receiving such material for research and/or educational purposes. This is in accordance with Title 17 U. S. C. section 107. Please note that distribution of articles doesn&#39;t constitute endorsement of the articles&#39; content; &quot;opposition&quot; articles are distributed to educate interested readership about contrary and unfavorable standpoints.<br><br>Your GLBT News moderator is Autumn.<br><br>Please direct all queries to <a rel=\"nofollow\"\n target=\"_blank\" href=\"mailto:GLBT_News-owner@yahoogroups.com\">GLBT_News-owner@yahoogroups.com</a>. <br><br>\n<center>\n<a rel=\"nofollow\" target=\"_blank\" href=\"http://groups.yahoo.com/group/FtM-trans/join\">\n<img src=\"https://ec.yimg.com/ec?url=http%3A%2F%2Fus.i1.yimg.com%2Fus.yimg.com%2Fi%2Fyg%2Fimg%2Fi%2Fus%2Fui%2Fjoin.gif&t=1572069218&sig=Rk2CYX3izrJyCLtObUevLQ--~E\" border=\"0\"\n alt=\"Click here to join FtM-trans\"><br>Click to join FtM-trans</a>\n</center></div>","website":"http://groups.yahoo.com/group/FtM-trans/","categoryId":1600064309,"dateCreated":1053819504,"name":"GLBT_News","membersVis":"MODERATORS","groupVis":"ALL","messagesVis":"SUBSCRIBERS","filesVis":"SUBSCRIBERS","linksVis":"SUBSCRIBERS","calendarVis":"SUBSCRIBERS","databaseVis":"NOBODY","pollsVis":"SUBSCRIBERS","postsVis":"SUBSCRIBERS","photosVis":"SUBSCRIBERS","messageAttachments":"ATTACHMENTS_DISABLED","messageModeration":"ALL_USERS_MODERATED","messagePost":"SUBSCRIBERS","memberShipType":"OPEN","replyTo":"LIST","unListed":false,"emailHidden":true,"photoModeration":false,"emailSubject":"[GLBT_News]","spamFiltering":false,"entityId":"@@groups_6442439c-3c9a-4922-88a7-d2dcdd3432ef","intlCode":"us","langCode":"en-US","adult":false,"pictureUrl":"https://xa.yimg.com/kq/groups/OIL5Rm_tetOPxkmnUQ--/homepage/name/28623.jpg","calView":3,"categoryName":"Human Rights","categoryPath":"/Cultures & Community/Issues and Causes/Human Rights/","isPhotomaticEnabled":true,"isPhotomaticEligible":true,"isPostAllowForNonMembers":false,"bucketId":"GB0"}}