{"ygPerms":{"resourceCapabilityList":[{"resourceType":"GROUP","capabilities":[{"name":"READ"},{"name":"JOIN"}]},{"resourceType":"PHOTO","capabilities":[]},{"resourceType":"FILE","capabilities":[]},{"resourceType":"MEMBER","capabilities":[]},{"resourceType":"LINK","capabilities":[]},{"resourceType":"CALENDAR","capabilities":[]},{"resourceType":"DATABASE","capabilities":[]},{"resourceType":"POLL","capabilities":[]},{"resourceType":"MESSAGE","capabilities":[]},{"resourceType":"PENDING_MESSAGE","capabilities":[]},{"resourceType":"ATTACHMENTS","capabilities":[]},{"resourceType":"PHOTOMATIC_ALBUMS","capabilities":[]},{"resourceType":"MEMBERSHIP_TYPE","capabilities":[]},{"resourceType":"POST","capabilities":[]},{"resourceType":"PIN","capabilities":[]}],"groupUrl":"groups.yahoo.com","intlCode":"us"},"comscore":"pageview_candidate","ygData":{"title":"Straight Men, FTM/GQ Partners","webDomain":"https://groups.yahoo.com/","emailDomain":"yahoogroups.com","domainUrlPrefix":"https://groups.yahoo.com/","description":"<div id=\"ygrps-yiv-242722276\">***NOTE: While new folks are welcome to join and start conversations, please note that this group has been serving more as an archive than a discussion for the past few years.***\n\nThis group is for straight or straightish non-trans male partners of FTMs, trans men, FTV/FCDs, and malewards-vectored genderqueer folk. This group is designed to fill a gap in support for the partners of transfolk and to be comfortable for straight non-trans guys to talk about how their partners&#39; gender identities and expressions affect them. \n\nThis group has now been opened to anyone, with moderator approval, who has a reason for wanting to talk about the issues straight guys face when their partners transition maleward. Please keep things on topic and supportive.</div>","categoryId":1600015362,"dateCreated":1117572440,"name":"str8menftmpartner","membersVis":"SUBSCRIBERS","groupVis":"ALL","messagesVis":"SUBSCRIBERS","filesVis":"SUBSCRIBERS","linksVis":"SUBSCRIBERS","calendarVis":"NOBODY","databaseVis":"SUBSCRIBERS","pollsVis":"SUBSCRIBERS","postsVis":"SUBSCRIBERS","photosVis":"SUBSCRIBERS","messageAttachments":"STORE_ON_SITE_AND_SEND_LINK_IN_EMAIL","messageModeration":"UNMODERATED","messagePost":"SUBSCRIBERS","memberShipType":"RESTRICTED","replyTo":"LIST","unListed":false,"emailHidden":false,"photoModeration":false,"emailSubject":"[str8menftmpartner]","spamFiltering":true,"intlCode":"us","langCode":"en-US","adult":false,"calView":3,"categoryName":"Men","categoryPath":"/Cultures & Community/Groups/Men/","isPhotomaticEnabled":true,"isPhotomaticEligible":true,"isPostAllowForNonMembers":false,"bucketId":"GB0"}}